{
  "tileset_name": "Pixel Platformer Terrain Tiles",
  "style": "16x16 pixel retro RPG/platformer",
  "tile_size": 16,
  "columns": 24,
  "rows": 2,
  "tiles": [
    {"id": 0, "type": "decor", "subtype": "grass_bush", "description": "圆形草丛装饰，边缘带黄色点缀"},
    {"id": 1, "type": "ground", "subtype": "grass_corner", "description": "L型草地转角，带泥土基底"},
    {"id": 2, "type": "decor", "subtype": "grass_small", "description": "小型草地区块，带黄色点缀"},
    {"id": 3, "type": "ground", "subtype": "grass_vertical", "description": "垂直长条形草地，带植被纹理"},
    {"id": 4, "type": "ground", "subtype": "dirt_vertical", "description": "垂直长条形泥土，表面有石块纹理"},
    {"id": 5, "type": "ground", "subtype": "grass_top", "description": "顶部草皮，下方泥土，水平平台"},
    {"id": 6, "type": "ground", "subtype": "dirt_top", "description": "顶部泥土，无草皮，水平平台"},
    {"id": 7, "type": "ground", "subtype": "grass_bottom", "description": "底部草皮，上方泥土，水平平台"},
    {"id": 8, "type": "ground", "subtype": "dirt_bottom", "description": "底部泥土，无草皮，水平平台"},
    {"id": 9, "type": "ground", "subtype": "dirt_small", "description": "小型泥土块，带石块纹理"},
    {"id": 10, "type": "ground", "subtype": "grass_small", "description": "小型草皮，边缘带草叶"},
    {"id": 11, "type": "ground", "subtype": "dirt_small", "description": "小型泥土块，带石块纹理"},
    {"id": 12, "type": "decor", "subtype": "grass_tiny", "description": "极小草叶装饰"},
    {"id": 13, "type": "ground", "subtype": "cliff_vertical", "description": "垂直悬崖，顶部草皮，侧面泥土岩壁"},
    {"id": 14, "type": "ground", "subtype": "cliff_corner", "description": "悬崖转角，顶部草皮，侧面泥土岩壁"},
    {"id": 15, "type": "ground", "subtype": "grass_single", "description": "单块草皮，下方泥土"},
    {"id": 16, "type": "ground", "subtype": "cliff_inner", "description": "内凹悬崖，草皮覆盖顶部与内侧"},
    {"id": 17, "type": "ground", "subtype": "cliff_outer", "description": "外凸悬崖，草皮覆盖顶部与外侧"},
    {"id": 18, "type": "ground", "subtype": "cliff_single", "description": "单块悬崖，顶部草皮，侧面泥土"},
    {"id": 19, "type": "ground", "subtype": "dirt_cliff", "description": "泥土悬崖，无草皮，侧面岩壁"},
    {"id": 20, "type": "ground", "subtype": "dirt_corner", "description": "泥土转角悬崖，无草皮"},
    {"id": 21, "type": "ground", "subtype": "dirt_platform", "description": "泥土平台，带洞穴入口"},
    {"id": 22, "type": "ground", "subtype": "dirt_single", "description": "单块泥土平台，侧面岩壁"},
    {"id": 23, "type": "ground", "subtype": "dirt_wall", "description": "垂直泥土岩壁，无草皮"},
    {"id": 24, "type": "decor", "subtype": "grass_bush_spiky", "description": "带尖刺边缘的圆形草丛"},
    {"id": 25, "type": "decor", "subtype": "grass_hole", "description": "带十字形破洞的草地区块"},
    {"id": 26, "type": "decor", "subtype": "grass_tiny", "description": "极小草叶装饰"},
    {"id": 27, "type": "decor", "subtype": "grass_small", "description": "小型草地区块，边缘尖刺"},
    {"id": 28, "type": "decor", "subtype": "grass_hole_spiky", "description": "带十字形破洞的尖刺边缘草地区块"},
    {"id": 29, "type": "ground", "subtype": "dirt_round", "description": "圆形泥土块，表面平整"},
    {"id": 30, "type": "ground", "subtype": "dirt_hole", "description": "带圆形孔洞的泥土块"},
    {"id": 31, "type": "decor", "subtype": "dirt_tiny", "description": "极小泥土装饰"},
    {"id": 32, "type": "ground", "subtype": "dirt_edge", "description": "水平泥土边缘，顶部平整"},
    {"id": 33, "type": "ground", "subtype": "dirt_arch", "description": "泥土拱形结构，可作洞穴入口"},
    {"id": 34, "type": "ground", "subtype": "dirt_arch_tiny", "description": "极小泥土拱形装饰"},
    {"id": 35, "type": "ground", "subtype": "cliff_slope_left", "description": "左倾斜坡悬崖，草皮覆盖顶部"},
    {"id": 36, "type": "ground", "subtype": "cliff_slope_right", "description": "右倾斜坡悬崖，草皮覆盖顶部"},
    {"id": 37, "type": "ground", "subtype": "cliff_bottom", "description": "悬崖底部草皮，上方泥土"},
    {"id": 38, "type": "ground", "subtype": "cliff_inner_slope", "description": "内凹斜坡悬崖，草皮覆盖顶部与内侧"},
    {"id": 39, "type": "ground", "subtype": "cliff_outer_slope", "description": "外凸斜坡悬崖，草皮覆盖顶部与外侧"},
    {"id": 40, "type": "ground", "subtype": "cliff_bottom_single", "description": "单块悬崖底部草皮，上方泥土"},
    {"id": 41, "type": "decor", "subtype": "grass_bush_round", "description": "圆形草丛，边缘柔和"},
    {"id": 42, "type": "decor", "subtype": "grass_hole_round", "description": "带十字形破洞的圆形草地区块"},
    {"id": 43, "type": "decor", "subtype": "grass_small", "description": "小型草地区块，边缘柔和"},
    {"id": 44, "type": "decor", "subtype": "grass_hole_soft", "description": "带十字形破洞的柔和边缘草地区块"},
    {"id": 45, "type": "ground", "subtype": "dirt_round", "description": "圆形泥土块，表面平整"},
    {"id": 46, "type": "ground", "subtype": "dirt_hole", "description": "带圆形孔洞的泥土块"},
    {"id": 47, "type": "ground", "subtype": "dirt_edge_soft", "description": "水平泥土边缘，顶部柔和"},
    {"id": 48, "type": "ground", "subtype": "dirt_arch_soft", "description": "泥土拱形结构，边缘柔和"}
  ]
}